<sketch id="8a5b3e85-fb8c-49d0-ac2b-5d4e3031cb07" time="1336242383062" xmlns:simpl="http://ecologylab.net/research/simplGuide/serialization/index.html"><shape id="00000000-749b-4b18-928b-564db91d8c60" time="1336242383062"><shape id="79d6e4a1-0157-48c9-a9d8-968c9801798c" time="1336242382532"><attributes><attr key="Primitive" value="Primitive" simpl:id="338319758"/></attributes><stroke id="e806b08c-2a05-4ee3-92c9-fa951d3f292c" time="1336242382532" draw_color="#64"><elem_stroke cap="2" width="2.0" miter_limit="10.0"/><point id="0250e9d8-c8c7-41a5-a5de-6dc5844c1497" time="1336256606263" x="64.0" y="170.0" simpl:id="521777441"></point><point id="f9b852b7-7138-4067-b420-6726dc400722" time="1336256606263" x="90.0" y="174.0" simpl:id="521777471"></point><point id="923d14ce-1524-429a-a455-ddd6501cc406" time="1336256606263" x="100.0" y="173.0" simpl:id="521777480"></point><point id="087e5219-47fa-45d5-a17d-3992faf73247" time="1336256606263" x="109.0" y="173.0" simpl:id="521777489"></point><point id="030458c8-a1f0-4565-aa2f-ffc1df856483" time="1336256606263" x="115.0" y="173.0" simpl:id="521777495"></point><point id="cf44b9e2-bd90-451d-860f-df2fddf6c59d" time="1336256606263" x="124.0" y="173.0" simpl:id="521777504"></point><point id="37059408-4ac2-4b72-88b4-85878b1eb11e" time="1336256606263" x="131.0" y="171.0" simpl:id="521777509"></point><point id="bd78511e-2dae-4a7e-90cb-e5d6813d3973" time="1336256606263" x="138.0" y="170.0" simpl:id="521777515"></point><point id="1054bc3a-f92b-4e88-9886-a324122e2de3" time="1336256606263" x="149.0" y="170.0" simpl:id="521777526"></point><point id="f484a03d-1c01-4d3c-ae12-4b6aae88cccd" time="1336256606263" x="157.0" y="168.0" simpl:id="521777532"></point><point id="2d773d64-a5ea-44d5-9c86-dbb93cbd8b05" time="1336256606263" x="167.0" y="167.0" simpl:id="521777541"></point><point id="f781c125-ca09-467e-acfd-355fd6185727" time="1336256606263" x="174.0" y="167.0" simpl:id="521777548"></point><point id="2c988e2c-2c17-4298-992a-843ad71e1771" time="1336256606263" x="184.0" y="167.0" simpl:id="521777558"></point><point id="d98827a6-2dc8-486d-8b92-5ce1d207e53e" time="1336256606263" x="190.0" y="167.0" simpl:id="521777564"></point><point id="364451ba-e1a7-4a26-b1da-e6d12b6df04f" time="1336256606263" x="195.0" y="167.0" simpl:id="521777569"></point><point id="3366c416-3ab0-4328-aa2e-856d052ddfd2" time="1336256606263" x="198.0" y="167.0" simpl:id="521777572"></point><point id="0a5d65df-f78a-42c8-9219-45ef7688d2eb" time="1336256606263" x="205.0" y="167.0" simpl:id="521777579"></point><point id="e39b7dc4-6ceb-48b7-805e-72b0be73b29f" time="1336256606263" x="207.0" y="167.0" simpl:id="521777581"></point><point id="6eca2550-e438-472f-862e-0b491faca591" time="1336256606263" x="214.0" y="165.0" simpl:id="521777586"></point><point id="7d10bf77-243a-4055-a443-5c7bfd1d7014" time="1336256606263" x="217.0" y="164.0" simpl:id="521777588"></point><point id="74bff22d-8701-405c-9647-2c195ef5dfe1" time="1336256606263" x="220.0" y="164.0" simpl:id="521777591"></point><point id="d37c2414-b883-40c3-a02f-925d0e844dca" time="1336256606263" x="226.0" y="162.0" simpl:id="521777595"></point><point id="4db6835c-e27c-474f-9349-a64d6c432dce" time="1336256606263" x="229.0" y="162.0" simpl:id="521777598"></point><point id="a79b06a5-55dd-4cb2-8888-0e3729747bad" time="1336256606263" x="235.0" y="161.0" simpl:id="521777603"></point><point id="520c6149-42ee-4d35-b8b3-d9cfc354fd11" time="1336256606263" x="238.0" y="159.0" simpl:id="521777604"></point><point id="35fb7ad3-a4a5-4fa7-bd4e-a044cffc0003" time="1336256606263" x="240.0" y="158.0" simpl:id="521777605"></point><point id="0e84fefa-673e-48c0-823f-475788318ef3" time="1336256606263" x="239.0" y="161.0" simpl:id="521777607"></point><point id="a2a29fbb-21f4-4327-8902-a1940751dba3" time="1336256606263" x="237.0" y="162.0" simpl:id="521777606"></point><point id="6439494e-7304-46e5-8bb8-d67ea77c92bd" time="1336256606263" x="235.0" y="164.0" simpl:id="521777606,1"></point><point id="2a594e5c-d256-4e2f-b3a4-cb8343ae70f2" time="1336256606263" x="232.0" y="167.0" simpl:id="521777606,2"></point><point id="bbd0908a-2652-4570-ab1e-f50a61110601" time="1336256606263" x="229.0" y="167.0" simpl:id="521777603,1"></point><parent id="b5ff6ee9-464a-439b-bdeb-d1b59e532ed8" time="1336242383062" simpl:id="-804400609"><elem_stroke cap="2" width="3.0" miter_limit="10.0"/><point simpl:ref="521777441"/><point simpl:ref="521777471"/><point simpl:ref="521777480"/><point simpl:ref="521777489"/><point simpl:ref="521777495"/><point simpl:ref="521777504"/><point simpl:ref="521777509"/><point simpl:ref="521777515"/><point simpl:ref="521777526"/><point simpl:ref="521777532"/><point simpl:ref="521777541"/><point simpl:ref="521777548"/><point simpl:ref="521777558"/><point simpl:ref="521777564"/><point simpl:ref="521777569"/><point simpl:ref="521777572"/><point simpl:ref="521777579"/><point simpl:ref="521777581"/><point simpl:ref="521777586"/><point simpl:ref="521777588"/><point simpl:ref="521777591"/><point simpl:ref="521777595"/><point simpl:ref="521777598"/><point simpl:ref="521777603"/><point simpl:ref="521777604"/><point simpl:ref="521777605"/><point simpl:ref="521777607"/><point simpl:ref="521777606"/><point simpl:ref="521777606,1"/><point simpl:ref="521777606,2"/><point simpl:ref="521777603,1"/><point id="a38771c4-a394-4cbb-8631-6326163d849e" time="1336256606263" x="226.0" y="170.0" simpl:id="521777603,2"></point><point id="f87295dc-66d9-41f0-b882-dc2b85a59da3" time="1336256606263" x="223.0" y="171.0" simpl:id="521777601"></point><point id="12d82592-0779-40d3-a931-24a883348f04" time="1336256606263" x="222.0" y="173.0" simpl:id="521777602"></point><point id="196866f1-a2cb-4c19-9a15-79a00aa8abc3" time="1336256606263" x="220.0" y="174.0" simpl:id="521777601,1"></point><point id="163893d8-5197-4bc3-ba97-f89aeddf9e6a" time="1336256606263" x="217.0" y="177.0" simpl:id="521777601,2"></point><point id="12e03c1b-3950-47e1-bde2-73da0788e96d" time="1336256606263" x="213.0" y="179.0" simpl:id="521777599"></point><point id="4644c50d-56a7-414a-b2d0-17cca4d3ac5e" time="1336256606263" x="210.0" y="182.0" simpl:id="521777599,1"></point><point id="add46fd0-8a0c-49d5-a585-c8e0ae72270b" time="1336256606263" x="208.0" y="183.0" simpl:id="521777598,1"></point><point id="8044a26f-32ec-42b3-aed6-090ce21de1f5" time="1336256606263" x="207.0" y="185.0" simpl:id="521777599,2"></point><point id="cfad9025-cd4d-4544-bfcb-7f5506e61274" time="1336256606263" x="202.0" y="189.0" simpl:id="521777598,2"></point><point id="a4fb62ab-56cf-43a9-a931-bc4b39b37c1a" time="1336256606263" x="200.0" y="191.0" simpl:id="521777598,3"></point><point id="6c50eb67-2468-4f64-9940-2efce135a72c" time="1336256606263" x="198.0" y="194.0" simpl:id="521777599,3"></point><point id="f5dec698-dc56-4a8c-a8e3-08adb0b5736a" time="1336256606263" x="196.0" y="197.0" simpl:id="521777600"></point><point id="4fff944c-c025-4e40-9335-5480ab3ad6c1" time="1336256606263" x="193.0" y="200.0" simpl:id="521777600,1"></point><point id="d2fc0362-4801-48b8-a6a5-06489c103e8a" time="1336256606263" x="188.0" y="207.0" simpl:id="521777602,1"></point><point id="dc2f09e7-a670-4a62-9a6c-51b1932cf371" time="1336256606263" x="186.0" y="212.0" simpl:id="521777605,1"></point><point id="80004cd2-c299-4e92-859d-3c2334f92d86" time="1336256606263" x="183.0" y="215.0" simpl:id="521777605,2"></point><point id="33f668e2-75e4-49b6-afbf-992fed8f86d2" time="1336256606263" x="180.0" y="218.0" simpl:id="521777605,3"></point><point id="8d932774-de6f-4246-a31c-65e93e54fbd3" time="1336256606263" x="175.0" y="227.0" simpl:id="521777609"></point><point id="ab00f443-68cb-47e1-9b09-f491aba9787e" time="1336256606263" x="173.0" y="230.0" simpl:id="521777610"></point><point id="8008d12b-9f54-4be9-b9d2-254896b48566" time="1336256606263" x="169.0" y="239.0" simpl:id="521777615"></point><point id="7e33456d-dc8c-444e-8d8a-9ea0f54e5478" time="1336256606263" x="167.0" y="243.0" simpl:id="521777617"></point><point id="54e2af63-48aa-4f04-a50f-2e6882800d3f" time="1336256606263" x="161.0" y="257.0" simpl:id="521777625"></point><point id="6f1fd91f-5432-4c30-842a-6724f7c9ddb8" time="1336256606263" x="156.0" y="269.0" simpl:id="521777632"></point><point id="a30e3159-2f34-48ed-acfa-aacc2d12d3ea" time="1336256606263" x="152.0" y="273.0" simpl:id="521777632,1"></point><point id="0b871a30-843f-436b-9aaa-a40386c0949c" time="1336256606263" x="146.0" y="284.0" simpl:id="521777637"></point><point id="a15f5d06-f660-4266-9ce9-e8ee3711f127" time="1336256606263" x="143.0" y="288.0" simpl:id="521777638"></point><point id="24e82089-f1b0-4cbd-8579-aae5da5463fc" time="1336256606263" x="137.0" y="297.0" simpl:id="521777641"></point><point id="b1e2aa1d-4201-41b2-88ae-a05fbf453ead" time="1336256606263" x="135.0" y="302.0" simpl:id="521777644"></point><point id="59e6dc13-edc0-4975-a4a7-f4e2b967b741" time="1336256606263" x="130.0" y="311.0" simpl:id="521777648"></point><point id="9d6c46ad-8cca-4059-8ca1-34ca7912f22f" time="1336256606263" x="127.0" y="314.0" simpl:id="521777648,1"></point><point id="5ae85d8c-eb25-4706-85a0-3de689c2c95d" time="1336256606263" x="124.0" y="320.0" simpl:id="521777651"></point><point id="80e7c9ca-f2b5-472a-a1fc-ea7ad5c5db64" time="1336256606263" x="122.0" y="324.0" simpl:id="521777653"></point><point id="5fdfd1f3-405c-4537-a02a-aa025c9cffc3" time="1336256606263" x="119.0" y="329.0" simpl:id="521777655"></point><point id="cae49d29-a263-4fac-aea8-551e3bed6b89" time="1336256606263" x="117.0" y="333.0" simpl:id="521777657"></point><point id="eab53f2b-a3f9-4c5e-9fef-8d3803f23ec9" time="1336256606263" x="112.0" y="341.0" simpl:id="521777660"></point><point id="16e3a129-8a47-4692-bd1d-8a3996117600" time="1336256606263" x="109.0" y="345.0" simpl:id="521777661"></point><point id="86ae5be4-4a7a-4780-aa9b-b4bf95c33503" time="1336256606263" x="105.0" y="353.0" simpl:id="521777665"></point><point id="4ed0f658-0307-42cb-9468-3ae041e14330" time="1336256606263" x="102.0" y="356.0" simpl:id="521777665,1"></point><point id="22c6eaeb-7275-4d62-9202-78bcba9cd2af" time="1336256606263" x="98.0" y="365.0" simpl:id="521777670"></point><point id="be884cf3-5117-4dcb-b8c3-953c2f8715dd" time="1336256606263" x="95.0" y="368.0" simpl:id="521777670,1"></point><point id="6443ee3b-efc2-4d7a-87a2-a4bce2b883c6" time="1336256606263" x="93.0" y="372.0" simpl:id="521777672"></point><point id="6dcae3f4-06f3-4acc-b01d-800321d19b12" time="1336256606263" x="86.0" y="380.0" simpl:id="521777673"></point><point id="22a96103-8273-45eb-919d-ccb3e2b84979" time="1336256606263" x="84.0" y="383.0" simpl:id="521777674"></point><point id="3b08e895-b553-414a-b19c-082260ef2899" time="1336256606263" x="79.0" y="387.0" simpl:id="521777673,1"></point><point id="fa8fa60f-77a9-4d29-84ab-82c7f74b36ae" time="1336256606263" x="76.0" y="389.0" simpl:id="521777672,1"></point><point id="43270494-a0c0-4aa6-890c-bf53f7ce226f" time="1336256606263" x="74.0" y="392.0" simpl:id="521777673,2"></point></parent></stroke><interpretations><interpretation label="line" confidence="1.0"/></interpretations></shape><shape id="022ebcb8-de8f-4242-aaef-c2666418155c" time="1336242383062"><attributes><attr simpl:ref="338319758"/></attributes><stroke id="cf2aeede-3ab1-44c4-85da-7ea005e0fc30" time="1336242383062" draw_color="#64"><elem_stroke cap="2" width="2.0" miter_limit="10.0"/><point simpl:ref="521777603,1"/><point simpl:ref="521777603,2"/><point simpl:ref="521777601"/><point simpl:ref="521777602"/><point simpl:ref="521777601,1"/><point simpl:ref="521777601,2"/><point simpl:ref="521777599"/><point simpl:ref="521777599,1"/><point simpl:ref="521777598,1"/><point simpl:ref="521777599,2"/><point simpl:ref="521777598,2"/><point simpl:ref="521777598,3"/><point simpl:ref="521777599,3"/><point simpl:ref="521777600"/><point simpl:ref="521777600,1"/><point simpl:ref="521777602,1"/><point simpl:ref="521777605,1"/><point simpl:ref="521777605,2"/><point simpl:ref="521777605,3"/><point simpl:ref="521777609"/><point simpl:ref="521777610"/><point simpl:ref="521777615"/><point simpl:ref="521777617"/><point simpl:ref="521777625"/><point simpl:ref="521777632"/><point simpl:ref="521777632,1"/><point simpl:ref="521777637"/><point simpl:ref="521777638"/><point simpl:ref="521777641"/><point simpl:ref="521777644"/><point simpl:ref="521777648"/><point simpl:ref="521777648,1"/><point simpl:ref="521777651"/><point simpl:ref="521777653"/><point simpl:ref="521777655"/><point simpl:ref="521777657"/><point simpl:ref="521777660"/><point simpl:ref="521777661"/><point simpl:ref="521777665"/><point simpl:ref="521777665,1"/><point simpl:ref="521777670"/><point simpl:ref="521777670,1"/><point simpl:ref="521777672"/><point simpl:ref="521777673"/><point simpl:ref="521777674"/><point simpl:ref="521777673,1"/><point simpl:ref="521777672,1"/><point simpl:ref="521777673,2"/><parent simpl:ref="-804400609"/></stroke><interpretations><interpretation label="line" confidence="1.0"/></interpretations></shape><shape id="00000000-7461-4b18-928b-564db84898c0" time="1336242382532"><attributes><attr simpl:ref="338319758"/></attributes><stroke id="00000000-743a-4b18-928b-564db8325970" time="1336242382532" draw_color="#64"><elem_stroke cap="2" width="2.0" miter_limit="10.0"/><point simpl:ref="521777441"/><point simpl:ref="521777471"/><point simpl:ref="521777480"/><point simpl:ref="521777489"/><point simpl:ref="521777495"/><point simpl:ref="521777504"/><point simpl:ref="521777509"/><point simpl:ref="521777515"/><point simpl:ref="521777526"/><point simpl:ref="521777532"/><point simpl:ref="521777541"/><point simpl:ref="521777548"/><point simpl:ref="521777558"/><point simpl:ref="521777564"/><point simpl:ref="521777569"/><point simpl:ref="521777572"/><point simpl:ref="521777579"/><point simpl:ref="521777581"/><point simpl:ref="521777586"/><point simpl:ref="521777588"/><point simpl:ref="521777591"/><point simpl:ref="521777595"/><point simpl:ref="521777598"/><point simpl:ref="521777603"/><point simpl:ref="521777604"/><point simpl:ref="521777605"/><point simpl:ref="521777607"/><point simpl:ref="521777606"/><point simpl:ref="521777606,1"/><point simpl:ref="521777606,2"/><point simpl:ref="521777603,1"/><parent simpl:ref="-804400609"/></stroke><interpretations><interpretation label="line" confidence="1.0"/></interpretations></shape><shape id="00000000-7467-4b18-928b-564db84a1790" time="1336242383062"><attributes><attr simpl:ref="338319758"/></attributes><stroke id="00000000-743b-4b18-928b-564db8330168" time="1336242383062" draw_color="#64"><elem_stroke cap="2" width="2.0" miter_limit="10.0"/><point simpl:ref="521777603,1"/><point simpl:ref="521777603,2"/><point simpl:ref="521777601"/><point simpl:ref="521777602"/><point simpl:ref="521777601,1"/><point simpl:ref="521777601,2"/><point simpl:ref="521777599"/><point simpl:ref="521777599,1"/><point simpl:ref="521777598,1"/><point simpl:ref="521777599,2"/><point simpl:ref="521777598,2"/><point simpl:ref="521777598,3"/><point simpl:ref="521777599,3"/><point simpl:ref="521777600"/><point simpl:ref="521777600,1"/><point simpl:ref="521777602,1"/><point simpl:ref="521777605,1"/><point simpl:ref="521777605,2"/><point simpl:ref="521777605,3"/><point simpl:ref="521777609"/><point simpl:ref="521777610"/><point simpl:ref="521777615"/><point simpl:ref="521777617"/><point simpl:ref="521777625"/><point simpl:ref="521777632"/><point simpl:ref="521777632,1"/><point simpl:ref="521777637"/><point simpl:ref="521777638"/><point simpl:ref="521777641"/><point simpl:ref="521777644"/><point simpl:ref="521777648"/><point simpl:ref="521777648,1"/><point simpl:ref="521777651"/><point simpl:ref="521777653"/><point simpl:ref="521777655"/><point simpl:ref="521777657"/><point simpl:ref="521777660"/><point simpl:ref="521777661"/><point simpl:ref="521777665"/><point simpl:ref="521777665,1"/><point simpl:ref="521777670"/><point simpl:ref="521777670,1"/><point simpl:ref="521777672"/><point simpl:ref="521777673"/><point simpl:ref="521777674"/><point simpl:ref="521777673,1"/><point simpl:ref="521777672,1"/><point simpl:ref="521777673,2"/><parent simpl:ref="-804400609"/></stroke><interpretations><interpretation label="line" confidence="1.0"/></interpretations></shape><interpretations><interpretation label="closedShape" confidence="1.0"/></interpretations></shape></sketch>